flet_dropzone/__init__.py
flet_dropzone/flet_dropzone.py
flutter/flet_dropzone/CHANGELOG.md
flutter/flet_dropzone/LICENSE
flutter/flet_dropzone/README.md
flutter/flet_dropzone/pubspec.yaml
flutter/flet_dropzone/lib/flet_dropzone.dart
flutter/flet_dropzone/lib/src/create_control.dart
flutter/flet_dropzone/lib/src/flet_dropzone.dart
flet_dropzone-0.2.0.dist-info/METADATA
flet_dropzone-0.2.0.dist-info/WHEEL
flet_dropzone-0.2.0.dist-info/top_level.txt
flet_dropzone-0.2.0.dist-info/RECORD
