Metadata-Version: 2.2
Name: flet-dropzone
Version: 0.2.0
Summary: Dropzone control for Flet
Author-email: KOGA Mitsuhiro <shiena.jp@gmail.com>
Project-URL: Homepage, https://github.com/shiena/flet-dropzone
Project-URL: Documentation, https://github.com/shiena/flet-dropzone
Project-URL: Repository, https://github.com/shiena/flet-dropzone
Project-URL: Issues, https://github.com/shiena/flet-dropzone/issues
Classifier: License :: OSI Approved :: Apache Software License
Requires-Python: >=3.9
Requires-Dist: flet>=0.27.0
